<tournament_quality_measures> 
<NegotiationOutcome Agent="bs: Group7_BS2 {Pconcede=0, Ppareto=0.5, averageOver=5.0, concedeFactor=0.3, concedeSteps=10.0, discount=0.0, e=0.3, hardcodefix=1.0, niceFactor=0.33, phase2=0.1, phase3=0.98} as: Group7_AS {acceptCurveApproach=0.8, acceptCurveStart=1.0, acceptCurveType=2, capWorstMinimal=0.6, capWorstSlope=-0.3, panicConcede=0.05, panicWhenBidsLeft=3, percentDurationWeight=0.25, timeWindow=0.2} om: Group7_OM: Adaptive Frequency Model  oms: Group7_OMS "> 
<TournamentQM average_time_of_agreement="0.7624306542637254" std_time_of_agreement="0.0" average_time_of_end_of_negotiation="0.7755981217472221" std_time_of_end_of_negotiation="0.0" average_rounds="14552.694444444445" std_rounds="0.0" percentage_of_agreement="94.44444444444444" average_util="0.8397949735449733" std_util="0.0" average_util_of_agreements="0.8891946778711483" average_discounted_util="0.8397949735449733" std_discounted_util="0.0" average_discounted_util_of_agreements="0.8891946778711483"> 
</TournamentQM> 
<UtilityBasedQM average_nash_distance="0.13887140949075089" average_nash_distance_of_agreements="0.08286523124702345" average_pareto_distance="0.06483973116106474" average_pareto_distance_of_agreements="0.007697986441545712" average_kalai_distance="0.12147185891666254" average_kalai_distance_of_agreements="0.06444217769798875" average_social_welfare="1.6890443121693122" average_social_welfare_of_agreements="1.7883998599439774"> 
</UtilityBasedQM> 
<trajectorAnalysisQM average_exploration="0.23220346464040714" average_joint_exploration="0.2459507405329146" perc_pareto_bids="0.32838171345860917" average_unfortunate_moves="0.19082422853437386" average_fortunate_moves="0.06680038228726021" average_nice_moves="0.13625490505558419" average_selfish_moves="0.08878621242850265" average_concession_moves="0.0773990877987004" average_silent_moves="0.4399351838955786"> 
</trajectorAnalysisQM> 
</NegotiationOutcome> 
<NegotiationOutcome Agent="HardHeaded"> 
<TournamentQM average_time_of_agreement="0.8182872296166666" std_time_of_agreement="0.0" average_time_of_end_of_negotiation="0.8383848339944443" std_time_of_end_of_negotiation="0.0" average_rounds="13250.305555555555" std_rounds="0.0" percentage_of_agreement="88.88888888888889" average_util="0.8334160052910051" std_util="0.0" average_util_of_agreements="0.9375930059523808" average_discounted_util="0.8334160052910051" std_discounted_util="0.0" average_discounted_util_of_agreements="0.9375930059523808"> 
</TournamentQM> 
<UtilityBasedQM average_nash_distance="0.20836483127634584" average_nash_distance_of_agreements="0.09803838023162441" average_pareto_distance="0.12384946365349049" average_pareto_distance_of_agreements="0.009799472686065742" average_kalai_distance="0.18124078501015936" average_kalai_distance_of_agreements="0.06752382818216461" average_social_welfare="1.5954332010582004" average_social_welfare_of_agreements="1.7948623511904755"> 
</UtilityBasedQM> 
<trajectorAnalysisQM average_exploration="0.03441862835705202" average_joint_exploration="0.2676850268595344" perc_pareto_bids="0.43071493493757534" average_unfortunate_moves="0.13909055842633458" average_fortunate_moves="0.019156066523338035" average_nice_moves="0.10717963041341037" average_selfish_moves="0.01310732994322681" average_concession_moves="0.014278733840034724" average_silent_moves="0.7071876808536555"> 
</trajectorAnalysisQM> 
</NegotiationOutcome> 
<NegotiationOutcome Agent="bs: Group7_BS2 {Pconcede=0, Ppareto=0.5, averageOver=5.0, concedeFactor=0.3, concedeSteps=10.0, discount=0.0, e=0.3, hardcodefix=0.0, niceFactor=0.33, phase2=0.1, phase3=0.95} as: Group7_AS {acceptCurveApproach=0.8, acceptCurveStart=1.0, acceptCurveType=2, capWorstMinimal=0.6, capWorstSlope=-0.3, panicConcede=0.05, panicWhenBidsLeft=3, percentDurationWeight=0.25, timeWindow=0.2} om: Group7_OM: Adaptive Frequency Model  oms: Group7_OMS "> 
<TournamentQM average_time_of_agreement="0.7964333037457144" std_time_of_agreement="0.0" average_time_of_end_of_negotiation="0.8020566857231481" std_time_of_end_of_negotiation="0.0" average_rounds="14827.666666666666" std_rounds="0.0" percentage_of_agreement="97.22222222222221" average_util="0.8505952380952378" std_util="0.0" average_util_of_agreements="0.8748979591836732" average_discounted_util="0.8505952380952378" std_discounted_util="0.0" average_discounted_util_of_agreements="0.8748979591836732"> 
</TournamentQM> 
<UtilityBasedQM average_nash_distance="0.09568969234795152" average_nash_distance_of_agreements="0.06725292813977536" average_pareto_distance="0.03207944267399274" average_pareto_distance_of_agreements="0.003388872710595726" average_kalai_distance="0.0793877443163649" average_kalai_distance_of_agreements="0.05048521016442912" average_social_welfare="1.7389467592592593" average_social_welfare_of_agreements="1.7886309523809525"> 
</UtilityBasedQM> 
<trajectorAnalysisQM average_exploration="0.2337951018880724" average_joint_exploration="0.2471750989504324" perc_pareto_bids="0.3361987442852644" average_unfortunate_moves="0.19129233153779715" average_fortunate_moves="0.06757694682468668" average_nice_moves="0.13720807641645746" average_selfish_moves="0.08917461842813525" average_concession_moves="0.07551571387505213" average_silent_moves="0.43923231291787146"> 
</trajectorAnalysisQM> 
</NegotiationOutcome> 
<NegotiationOutcome Agent="Gahboninho V3"> 
<TournamentQM average_time_of_agreement="0.8109363319648147" std_time_of_agreement="0.0" average_time_of_end_of_negotiation="0.8109363319648147" std_time_of_end_of_negotiation="0.0" average_rounds="16216.444444444445" std_rounds="0.0" percentage_of_agreement="100.0" average_util="0.9166071428571426" std_util="0.0" average_util_of_agreements="0.9166071428571426" average_discounted_util="0.9166071428571426" std_discounted_util="0.0" average_discounted_util_of_agreements="0.9166071428571426"> 
</TournamentQM> 
<UtilityBasedQM average_nash_distance="0.05377624678265847" average_nash_distance_of_agreements="0.05377624678265847" average_pareto_distance="0.0088402761492798" average_pareto_distance_of_agreements="0.0088402761492798" average_kalai_distance="0.05426278308571679" average_kalai_distance_of_agreements="0.05426278308571679" average_social_welfare="1.7854679232804231" average_social_welfare_of_agreements="1.7854679232804231"> 
</UtilityBasedQM> 
<trajectorAnalysisQM average_exploration="0.003202308009488281" average_joint_exploration="0.19975732241678898" perc_pareto_bids="0.6599186859064845" average_unfortunate_moves="8.287703270697957E-4" average_fortunate_moves="7.441537610051767E-5" average_nice_moves="5.097950429568587E-4" average_selfish_moves="1.8301911199257199E-4" average_concession_moves="5.846168466829276E-4" average_silent_moves="0.9978193832951973"> 
</trajectorAnalysisQM> 
</NegotiationOutcome> 
<NegotiationOutcome Agent="bs: 2011 - The Negotiator  as: 2011 - The Negotiator  om: CUHKFrequencyModelV2  oms: Best bid {t=1.0}"> 
<TournamentQM average_time_of_agreement="0.6959481304805554" std_time_of_agreement="0.0" average_time_of_end_of_negotiation="0.6959481304805554" std_time_of_end_of_negotiation="0.0" average_rounds="15173.277777777777" std_rounds="0.0" percentage_of_agreement="100.0" average_util="0.8853257275132274" std_util="0.0" average_util_of_agreements="0.8853257275132274" average_discounted_util="0.8853257275132274" std_discounted_util="0.0" average_discounted_util_of_agreements="0.8853257275132274"> 
</TournamentQM> 
<UtilityBasedQM average_nash_distance="0.08019578793006799" average_nash_distance_of_agreements="0.08019578793006799" average_pareto_distance="0.001388888888888884" average_pareto_distance_of_agreements="0.001388888888888884" average_kalai_distance="0.06133141009278101" average_kalai_distance_of_agreements="0.06133141009278101" average_social_welfare="1.7751339285714287" average_social_welfare_of_agreements="1.7751339285714287"> 
</UtilityBasedQM> 
<trajectorAnalysisQM average_exploration="0.003011216062299877" average_joint_exploration="0.2765154862555104" perc_pareto_bids="0.8347249379655786" average_unfortunate_moves="0.009577992462164113" average_fortunate_moves="0.007379639975479791" average_nice_moves="0.0020448010442164904" average_selfish_moves="0.007343144870829491" average_concession_moves="0.007772472733567307" average_silent_moves="0.9658819489137428"> 
</trajectorAnalysisQM> 
</NegotiationOutcome> 
<NegotiationOutcome Agent="bs: Group7_BS2 {Pconcede=0, Ppareto=0.5, averageOver=5.0, concedeFactor=0.3, concedeSteps=10.0, discount=0.0, e=0.3, hardcodefix=1.0, niceFactor=0.33, phase2=0.1, phase3=0.90} as: Group7_AS {acceptCurveApproach=0.8, acceptCurveStart=1.0, acceptCurveType=2, capWorstMinimal=0.6, capWorstSlope=-0.3, panicConcede=0.05, panicWhenBidsLeft=3, percentDurationWeight=0.25, timeWindow=0.2} om: Group7_OM: Adaptive Frequency Model  oms: Group7_OMS "> 
<TournamentQM average_time_of_agreement="0.7610064034199999" std_time_of_agreement="0.0" average_time_of_end_of_negotiation="0.7676144889694444" std_time_of_end_of_negotiation="0.0" average_rounds="15259.666666666666" std_rounds="0.0" percentage_of_agreement="97.22222222222221" average_util="0.8302959656084653" std_util="0.0" average_util_of_agreements="0.8540187074829929" average_discounted_util="0.8302959656084653" std_discounted_util="0.0" average_discounted_util_of_agreements="0.8540187074829929"> 
</TournamentQM> 
<UtilityBasedQM average_nash_distance="0.10777576415036988" average_nash_distance_of_agreements="0.07968431627940566" average_pareto_distance="0.03715945485660167" average_pareto_distance_of_agreements="0.008614028098422051" average_kalai_distance="0.0959753749556297" average_kalai_distance_of_agreements="0.0675467731076729" average_social_welfare="1.7280439814814812" average_social_welfare_of_agreements="1.7774166666666662"> 
</UtilityBasedQM> 
<trajectorAnalysisQM average_exploration="0.238319517337079" average_joint_exploration="0.25083199604848677" perc_pareto_bids="0.3374883389037654" average_unfortunate_moves="0.18575648284070492" average_fortunate_moves="0.06751667605628339" average_nice_moves="0.13021252865896768" average_selfish_moves="0.09469835058875267" average_concession_moves="0.08248117768084734" average_silent_moves="0.439334784174444"> 
</trajectorAnalysisQM> 
</NegotiationOutcome> 
</tournament_quality_measures> 
